flet_easy/__init__.py
flet_easy/fletEasy.py
flet_easy/inheritance.py
flet_easy/route.py
flet_easy/view_404.py
flet_easy_test-0.1.0.dist-info/METADATA
flet_easy_test-0.1.0.dist-info/WHEEL
flet_easy_test-0.1.0.dist-info/licenses/LICENSE
flet_easy_test-0.1.0.dist-info/RECORD
