Metadata-Version: 2.1
Name: flet-easy-test
Version: 0.1.0
Summary: Flet-Easy is a package created as a Flet add-on, designed to be easy to use with a cleaner order in the code, having many customizable features.
Keywords: flet easy flet python flet router
Author-Email: Daxexs <Daxexsdev@gmail.com>
License: apache-2.0
Classifier: Topic :: Software Development :: Build Tools
Classifier: Programming Language :: Python :: 3
Classifier: Programming Language :: Python :: 3.8
Classifier: Programming Language :: Python :: 3.9
Classifier: Programming Language :: Python :: 3.10
Classifier: Programming Language :: Python :: 3.11
Classifier: Programming Language :: Python :: 3.12
Project-URL: Homepage, https://github.com/Daxexs
Project-URL: Repository, https://github.com/Daxexs/flet-easy
Project-URL: Documentation, https://github.com/Daxexs/flet-easy/blob/main/README.md
Project-URL: Changelog, https://github.com/Daxexs/flet-easy/blob/main/README.md
Requires-Python: >=3.8
Requires-Dist: flet
Requires-Dist: parse
